myboot/__init__.py
myboot/cli.py
myboot/exceptions.py
myboot/core/__init__.py
myboot/core/application.py
myboot/core/auto_configuration.py
myboot/core/config.py
myboot/core/container.py
myboot/core/decorators.py
myboot/core/logger.py
myboot/core/scheduler.py
myboot/core/server.py
myboot/core/di/__init__.py
myboot/core/di/container.py
myboot/core/di/decorators.py
myboot/core/di/providers.py
myboot/core/di/registry.py
myboot/jobs/__init__.py
myboot/jobs/scheduled_job.py
myboot/utils/__init__.py
myboot/utils/async_utils.py
myboot/utils/common.py
myboot/utils/path_utils.py
myboot/web/__init__.py
myboot/web/decorators.py
myboot/web/exceptions.py
myboot/web/middleware.py
myboot/web/models.py
myboot/web/response.py
myboot-0.1.10.dist-info/METADATA
myboot-0.1.10.dist-info/WHEEL
myboot-0.1.10.dist-info/entry_points.txt
myboot-0.1.10.dist-info/licenses/LICENSE
myboot-0.1.10.dist-info/RECORD
